bip38/__init__.py
bip38/bip38.py
bip38/const.py
bip38/crypto.py
bip38/cryptocurrencies.py
bip38/exceptions.py
bip38/info.py
bip38/p2pkh_address.py
bip38/utils.py
bip38/wif.py
bip38/libs/__init__.py
bip38/libs/base58.py
bip38/libs/ripemd160.py
bip38/secp256k1/__init__.py
bip38/secp256k1/point.py
bip38/secp256k1/private_key.py
bip38/secp256k1/public_key.py
bip38-1.4.1.dist-info/licenses/LICENSE
examples/__init__.py
"examples/ec-multiply, compression, lot-&-sequence.py"
"examples/ec-multiply, compression, no-lot-&-sequence.py"
"examples/ec-multiply, no-compression, lot-&-sequence.py"
"examples/ec-multiply, no-compression, no-lot-&-sequence.py"
"examples/no-ec-multiply, compression.py"
"examples/no-ec-multiply, no-compression.py"
bip38-1.4.1.dist-info/METADATA
bip38-1.4.1.dist-info/WHEEL
bip38-1.4.1.dist-info/top_level.txt
bip38-1.4.1.dist-info/RECORD
