Metadata-Version: 2.4
Name: bip38
Version: 1.4.1
Summary: A Python library for implementation of Bitcoin Improvement Proposal - 0038 / BIP38 protocol.
Home-page: https://hdwallet.io
Author: Meheret Tesfaye Batu
Author-email: meherett.batu@gmail.com
License: MIT
Project-URL: Tracker, https://hdwallet.io/issues
Project-URL: Source, https://github.com/hdwallet-io/python-bip38
Project-URL: Changelog, https://github.com/hdwallet-io/python-bip38/blob/master/CHANGELOG.md
Project-URL: Documentation, https://bip38.readthedocs.com
Keywords: bip38,bitcoin,private-key,hdwallet,encrypt,decrypt,passphrase,wif,security
Classifier: Development Status :: 5 - Production/Stable
Classifier: License :: OSI Approved :: MIT License
Classifier: Programming Language :: Python :: 3.9
Classifier: Programming Language :: Python :: 3.10
Classifier: Programming Language :: Python :: 3.11
Classifier: Programming Language :: Python :: 3.12
Classifier: Programming Language :: Python :: 3.13
Classifier: Topic :: Software Development :: Libraries :: Python Modules
Requires-Python: >=3.9,<4
License-File: LICENSE
Requires-Dist: pyaes<2,>=1.6.1
Requires-Dist: pycryptodome<4,>=3.23.0
Requires-Dist: six<2,>=1.16.0
Requires-Dist: ecdsa<1,>=0.18.0
Provides-Extra: docs
Requires-Dist: sphinx<9,>=8.1.3; extra == "docs"
Requires-Dist: furo==2024.8.6; extra == "docs"
Provides-Extra: tests
Requires-Dist: pytest<9,>=8.3.2; extra == "tests"
Requires-Dist: coverage<8,>=7.6.4; extra == "tests"
Requires-Dist: tox<5,>=4.23.2; extra == "tests"
Dynamic: author
Dynamic: author-email
Dynamic: classifier
Dynamic: description
Dynamic: description-content-type
Dynamic: home-page
Dynamic: keywords
Dynamic: license
Dynamic: license-file
Dynamic: project-url
Dynamic: provides-extra
Dynamic: requires-dist
Dynamic: requires-python
Dynamic: summary
